setup.py
httplaceholder/__init__.py
httplaceholder/htt_placeholder_api.py
httplaceholder/version.py
httplaceholder.egg-info/PKG-INFO
httplaceholder.egg-info/SOURCES.txt
httplaceholder.egg-info/dependency_links.txt
httplaceholder.egg-info/requires.txt
httplaceholder.egg-info/top_level.txt
httplaceholder/models/__init__.py
httplaceholder/models/condition_check_result_model.py
httplaceholder/models/request_parameters_model.py
httplaceholder/models/request_result_model.py
httplaceholder/models/stub_basic_authentication_model.py
httplaceholder/models/stub_conditions_model.py
httplaceholder/models/stub_execution_result_model.py
httplaceholder/models/stub_model.py
httplaceholder/models/stub_response_model.py
httplaceholder/models/stub_response_writer_result_model.py
httplaceholder/models/stub_url_condition_model.py
httplaceholder/models/stub_xpath_model.py