Metadata-Version: 1.0
Name: httplaceholder
Version: 0.5.0
Summary: httplaceholder
Home-page: https://github.com/dukeofharen/httplaceholder_python
Author: Duco
Author-email: mail@ducode.org
License: UNKNOWN
Keywords: Swagger,httplaceholder
Platform: UNKNOWN
